zlgsendcan/__init__.py
zlgsendcan/example_test.py
zlgsendcan/frozen_dir.py
zlgsendcan/get_conf_info.py
zlgsendcan/parseDBC.py
zlgsendcan/yaml_util.py
zlgsendcan/zlgcan1.py
zlgsendcan/zlgcan_1.dll
zlgsendcan/zlgserver.py
zlgsendcan/kerneldlls/CANDTU_NET.dll
zlgsendcan/kerneldlls/CANDTU_x64.dll
zlgsendcan/kerneldlls/CANDevCore.dll
zlgsendcan/kerneldlls/CANDevice.dll
zlgsendcan/kerneldlls/CANETE.dll
zlgsendcan/kerneldlls/CANET_TCP.dll
zlgsendcan/kerneldlls/CANFDCOM.dll
zlgsendcan/kerneldlls/CANFDNET.dll
zlgsendcan/kerneldlls/CANWIFI_TCP.dll
zlgsendcan/kerneldlls/CANWIFI_UDP.dll
zlgsendcan/kerneldlls/USBCAN.dll
zlgsendcan/kerneldlls/USBCAN.xml
zlgsendcan/kerneldlls/USBCANFD.dll
zlgsendcan/kerneldlls/USBCANFD800U.dll
zlgsendcan/kerneldlls/VCI_USBCAN2.xml
zlgsendcan/kerneldlls/VirtualUSBCAN.dll
zlgsendcan/kerneldlls/ZlgCloud.dll
zlgsendcan/kerneldlls/dll_cfg.ini
zlgsendcan-1.2.1.dist-info/METADATA
zlgsendcan-1.2.1.dist-info/WHEEL
zlgsendcan-1.2.1.dist-info/top_level.txt
zlgsendcan-1.2.1.dist-info/RECORD
