Metadata-Version: 2.1
Name: zlgsendcan
Version: 1.2.1
Summary: zlg send canmsg
Home-page: UNKNOWN
Author: liuzhong
Author-email: liuzhong@auto-link.com.cn
License: UNKNOWN
Platform: UNKNOWN
Requires-Dist: cantools
Requires-Dist: PyYAML
